pyhwid/__init__.py
pyhwid/core.py
pyhwid/wrapper.py
pyhwid-0.0.1.dist-info/LICENSE
pyhwid-0.0.1.dist-info/METADATA
pyhwid-0.0.1.dist-info/WHEEL
pyhwid-0.0.1.dist-info/top_level.txt
pyhwid-0.0.1.dist-info/RECORD
