Metadata-Version: 2.1
Name: pyhwid
Version: 0.0.1
Summary: HWID generator for Windows & MacOS
Home-page: https://github.com/aaronlyy/pyhwid
Author: Aaron Levi (aaronlyy) Can
Author-email: aaronlevican@gmail.com
License: MIT
Classifier: License :: OSI Approved :: MIT License
Classifier: Programming Language :: Python :: 3.6
Classifier: Programming Language :: Python :: 3.7
Classifier: Programming Language :: Python :: 3.8
Classifier: Programming Language :: Python :: 3.9
Classifier: Programming Language :: Python :: 3.10
Classifier: Programming Language :: Python :: 3.11
Classifier: Programming Language :: Python :: 3.12
Requires-Python: >=3.6
License-File: LICENSE
